calver/__init__.py
calver/commands.py
calver/integration.py
calver_pinning-2021.2.10.dist-info/LICENSE
calver_pinning-2021.2.10.dist-info/METADATA
calver_pinning-2021.2.10.dist-info/WHEEL
calver_pinning-2021.2.10.dist-info/entry_points.txt
calver_pinning-2021.2.10.dist-info/top_level.txt
calver_pinning-2021.2.10.dist-info/RECORD
