Metadata-Version: 2.1
Name: calver-pinning
Version: 2021.2.10
Summary: Setuptools extension for CalVer package versions (fork)
Home-page: https://github.com/di/calver
Author: Dustin Ingram
Author-email: di@python.org
Maintainer: Jamie Bliss
Maintainer-email: jamie@ivyleav.es
License: UNKNOWN
Keywords: calver
Platform: UNKNOWN
Classifier: Intended Audience :: Developers
Classifier: Topic :: Software Development :: Build Tools
Classifier: License :: OSI Approved :: Apache Software License
Classifier: Programming Language :: Python :: 3
Requires-Dist: setuptools
